lightbulb/ext/tungsten/__init__.py
lightbulb/ext/tungsten/tungsten.py
lightbulb_ext_tungsten-0.1.dist-info/LICENSE
lightbulb_ext_tungsten-0.1.dist-info/METADATA
lightbulb_ext_tungsten-0.1.dist-info/WHEEL
lightbulb_ext_tungsten-0.1.dist-info/top_level.txt
lightbulb_ext_tungsten-0.1.dist-info/RECORD
