Metadata-Version: 2.1
Name: lightbulb-ext-tungsten
Version: 0.1
Summary: An add-on for hikari-lightbulb providing an alternative for handling component interactions.
Home-page: https://github.com/Christian-Tarello/lightbulb-ext-tungsten
Author: Christian-Tarello
Author-email: 
License: GPL-3.0
Platform: UNKNOWN
Classifier: Development Status :: 3 - Alpha
Classifier: Framework :: AsyncIO
Classifier: Intended Audience :: Developers
Classifier: Natural Language :: English
Classifier: Topic :: Software Development :: Libraries :: Python Modules
Classifier: Programming Language :: Python :: 3.8
Classifier: Programming Language :: Python :: 3.9
Classifier: Programming Language :: Python :: 3.10
Classifier: Programming Language :: Python :: Implementation :: CPython
Classifier: Programming Language :: Python :: 3 :: Only
Classifier: Topic :: Software Development :: Libraries
Classifier: Topic :: Software Development :: Libraries :: Application Frameworks
Classifier: Topic :: Software Development :: Libraries :: Python Modules
Requires-Python: >=3.8.0,<3.11
License-File: LICENSE
